trello_track/__init__.py
trello_track/__main__.py
trello_track-0.0.1.dist-info/LICENSE
trello_track-0.0.1.dist-info/METADATA
trello_track-0.0.1.dist-info/WHEEL
trello_track-0.0.1.dist-info/entry_points.txt
trello_track-0.0.1.dist-info/top_level.txt
trello_track-0.0.1.dist-info/RECORD
