Metadata-Version: 2.1
Name: trello-track
Version: 0.0.1
Summary: Tracks running processes on Trello
Home-page: https://github.com/seanmacavaney/trello-track
Author: Sean MacAvaney
Author-email: dev.sean.macavaney@gmail.com
License: UNKNOWN
Platform: UNKNOWN
Requires-Python: >=3.6
